structures.py
structures-0.9.5.dist-info/DESCRIPTION.rst
structures-0.9.5.dist-info/METADATA
structures-0.9.5.dist-info/RECORD
structures-0.9.5.dist-info/WHEEL
structures-0.9.5.dist-info/metadata.json
structures-0.9.5.dist-info/top_level.txt
structures-0.9.5.dist-info/zip-safe
