Metadata-Version: 1.1
Name: structures
Version: 0.9.5
Summary: Declarative binary building and parsing: simple, fast and extensible
Home-page: https://github.com/malinoff/structures
Author: Dmitry Malinovsky (aka malinoff)
Author-email: damalinov@gmail.com
License: Apache 2.0
Keywords: structures,declarative,data structure,binary,parser,builder,pack,unpack
Platform: UNKNOWN
Classifier: Development Status :: 4 - Beta
Classifier: Intended Audience :: Developers
Classifier: Intended Audience :: Education
Classifier: Intended Audience :: Information Technology
Classifier: Intended Audience :: Science/Research
Classifier: Intended Audience :: System Administrators
Classifier: Intended Audience :: Telecommunications Industry
Classifier: License :: OSI Approved :: Apache Software License
Classifier: Programming Language :: Python :: 3 :: Only
